threedidepth/__init__.py
threedidepth/calculate.py
threedidepth/commands.py
threedidepth/fixes.py
threedidepth/morton.py
threedidepth/tiffs.py
threedidepth-0.7.4.dist-info/licenses/LICENSE
threedidepth-0.7.4.dist-info/METADATA
threedidepth-0.7.4.dist-info/WHEEL
threedidepth-0.7.4.dist-info/entry_points.txt
threedidepth-0.7.4.dist-info/top_level.txt
threedidepth-0.7.4.dist-info/RECORD
