Metadata-Version: 2.4
Name: threedidepth
Version: 0.7.4
Summary: Calculate waterdepths for 3Di results.
Home-page: https://github.com/nens/threedidepth
Author: Arjan Verkerk
Author-email: arjan.verkerk@nelen-schuurmans.nl
License: BSD license
Keywords: threedidepth
Classifier: Development Status :: 4 - Beta
Classifier: Intended Audience :: Developers
Classifier: License :: OSI Approved :: BSD License
Classifier: Natural Language :: English
Classifier: Programming Language :: Python :: 3
Classifier: Programming Language :: Python :: 3.6
Classifier: Topic :: Scientific/Engineering
Requires-Python: >=3.5
License-File: LICENSE
Requires-Dist: h5py
Requires-Dist: h5netcdf
Requires-Dist: numpy
Requires-Dist: scipy
Requires-Dist: threedigrid
Provides-Extra: test
Requires-Dist: flake8; extra == "test"
Requires-Dist: pytest; extra == "test"
Requires-Dist: pytest-cov; extra == "test"
Dynamic: author
Dynamic: author-email
Dynamic: classifier
Dynamic: description
Dynamic: home-page
Dynamic: keywords
Dynamic: license
Dynamic: license-file
Dynamic: provides-extra
Dynamic: requires-dist
Dynamic: requires-python
Dynamic: summary
